odoo/addons/crm_event/README.rst
odoo/addons/crm_event/__init__.py
odoo/addons/crm_event/__manifest__.py
odoo/addons/crm_event/i18n/crm_event.pot
odoo/addons/crm_event/i18n/es.po
odoo/addons/crm_event/i18n/it.po
odoo/addons/crm_event/models/__init__.py
odoo/addons/crm_event/models/crm_lead.py
odoo/addons/crm_event/models/event_type.py
odoo/addons/crm_event/readme/CONFIGURE.md
odoo/addons/crm_event/readme/CONTRIBUTORS.md
odoo/addons/crm_event/readme/DESCRIPTION.md
odoo/addons/crm_event/readme/USAGE.md
odoo/addons/crm_event/reports/__init__.py
odoo/addons/crm_event/reports/event_type_report.py
odoo/addons/crm_event/reports/event_type_report_view.xml
odoo/addons/crm_event/security/ir.model.access.csv
odoo/addons/crm_event/static/description/icon.png
odoo/addons/crm_event/static/description/index.html
odoo/addons/crm_event/tests/__init__.py
odoo/addons/crm_event/tests/test_event_type.py
odoo/addons/crm_event/views/crm_lead_view.xml
odoo/addons/crm_event/views/event_type_view.xml
odoo_addon_crm_event-17.0.1.0.1.dist-info/METADATA
odoo_addon_crm_event-17.0.1.0.1.dist-info/WHEEL
odoo_addon_crm_event-17.0.1.0.1.dist-info/top_level.txt
odoo_addon_crm_event-17.0.1.0.1.dist-info/RECORD
